fedex_api.py
fedexapi_chnoma-1.2.4.dist-info/LICENSE
fedexapi_chnoma-1.2.4.dist-info/METADATA
fedexapi_chnoma-1.2.4.dist-info/WHEEL
fedexapi_chnoma-1.2.4.dist-info/top_level.txt
fedexapi_chnoma-1.2.4.dist-info/RECORD
