Metadata-Version: 2.1
Name: fedexapi-chnoma
Version: 1.2.4
Summary: A module I devloped to abstract the Fedex API for use in my programs.
Author-email: "Adrian J. Arnett" <adrianarnett0@gmail.com>
Project-URL: Homepage, https://github.com/chnoma/fedex-api
Project-URL: Bug Tracker, https://github.com/chnoma/fedex-api/issues
Keywords: FedEx,API
Classifier: Programming Language :: Python :: 3
Classifier: License :: OSI Approved :: MIT License
Classifier: Operating System :: OS Independent
Requires-Python: >=3.7
License-File: LICENSE
Requires-Dist: requests
